{
    "std": [
        "std",
        "reYIK",
        "module",
        1
    ],
    "scoreboard_tid_entry": [
        "scoreboard_tid_entry",
        "nFM25",
        "module",
        2
    ],
    "scoreboard": [
        "scoreboard",
        "snDLU",
        "module",
        3
    ],
    "next_active_thread_logic": [
        "next_active_thread_logic",
        "cWQzx",
        "module",
        4
    ],
    "priority_encoder_8bit": [
        "priority_encoder_8bit",
        "rtTEU",
        "module",
        5
    ],
    "priority_encoder_64bit_0000": [
        "priority_encoder_64bit_0000",
        "qbEQB",
        "module",
        9
    ],
    "sync_fifo": [
        "sync_fifo",
        "gWQCM",
        "module",
        8
    ],
    "sync_fifo_read_unreg": [
        "sync_fifo_read_unreg",
        "vKZ9E",
        "module",
        10
    ],
    "next_thread_logic_top_testbench": [
        "next_thread_logic_top_testbench",
        "ySh58",
        "module",
        6
    ],
    "...MASTER...": [
        "SIM",
        "amcQw",
        "module",
        7
    ]
}